{"stat.flyOneCm":10292,"stat.killEntity.Skeleton":2,"stat.walkOneCm":6504,"stat.jump":14,"stat.playOneMinute":3265,"stat.leaveGame":1,"stat.sneakTime":96,"stat.useItem.harshenuniverse.soul_harsher_sword":22,"stat.killEntity.Spider":2,"stat.damageDealt":2637,"stat.crouchOneCm":197,"stat.killEntity.Zombie":1,"stat.timeSinceDeath":3265,"stat.killEntity.soul_shooter":15,"stat.mobKills":26,"stat.sprintOneCm":77,"stat.useItem.minecraft.stone_slab2":3,"stat.useItem.minecraft.spawn_egg":20,"stat.killEntity.Creeper":4,"stat.pickup.actuallyadditions.item_solidified_experience":3}